{
  "code": "N21000441",
  "name": "Faughan_F",
  "comment": "This json includes data for the MDM app",
  "type": "sdz",
  "count": 850,
  "parents": [
    {
      "code": "N10000503",
      "name": "Faughan",
      "type": "dea"
    },
    {
      "code": "N09000005",
      "name": "Derry City and Strabane",
      "type": "lgd"
    },
    {
      "code": "N92000002",
      "name": "Northern Ireland",
      "type": "ctry"
    }
  ],
  "children": [],
  "bounds": [-7.3477, 54.9496, -7.3658, 54.9685],
  "data": {
    "ranks": {
      "mdm": 475,
      "income": 427,
      "below60": 460,
      "employment": 394,
      "emprop": 467,
      "health": 472,
      "education": 544,
      "services": 199
    },
    "population": 2867,
    "hectares": 137.958
  }
}
